Metadata-Version: 1.0
Name: newtonraphson
Version: 0.1
Summary: Implementation of Newton-raphson method
Home-page: UNKNOWN
Author: UNKNOWN
Author-email: UNKNOWN
License: UNKNOWN
Platform: UNKNOWN
